dnnlab/__init__.py
dnnlab/adversarial_attacks/__init__.py
dnnlab/adversarial_attacks/images/__init__.py
dnnlab/adversarial_attacks/images/fgsm.py
dnnlab/callbacks/__init__.py
dnnlab/callbacks/tensorboard_imagelabel_callback.py
dnnlab/errors/__init__.py
dnnlab/errors/dnnlab_exceptions.py
dnnlab/generative_models/__init__.py
dnnlab/generative_models/images/__init__.py
dnnlab/generative_models/images/cgan.py
dnnlab/generative_models/images/cycle_gan.py
dnnlab/generative_models/images/gan.py
dnnlab/image_detection/__init__.py
dnnlab/image_detection/yolo.py
dnnlab/image_to_image/__init__.py
dnnlab/image_to_image/nn.py
dnnlab/input_pipeline/__init__.py
dnnlab/input_pipeline/img.py
dnnlab/input_pipeline/img_img.py
dnnlab/input_pipeline/img_label.py
dnnlab/input_pipeline/triplet_net.py
dnnlab/input_pipeline/yolo.py
dnnlab/input_pipeline/augmentation/__init__.py
dnnlab/input_pipeline/augmentation/img_classification_augmentation.py
dnnlab/input_pipeline/augmentation/yolo_augmentation.py
dnnlab/interpretability/__init__.py
dnnlab/interpretability/grad_cam.py
dnnlab/layers/__init__.py
dnnlab/layers/non_local_block.py
dnnlab/layers/preprocessing.py
dnnlab/layers/se_block.py
dnnlab/layers/yolo_decoder.py
dnnlab/losses/__init__.py
dnnlab/losses/ocr.py
dnnlab/losses/yolo.py
dnnlab/losses/triplet_net/__init__.py
dnnlab/losses/triplet_net/triplet_loss.py
dnnlab/losses/triplet_net/triplet_mining.py
dnnlab/metric_learning/__init__.py
dnnlab/metric_learning/knn_classifier.py
dnnlab/metric_learning/similarity_attention.py
dnnlab/metric_learning/triplet_net.py
dnnlab/metric_learning/triplet_utils.py
dnnlab/utils/__init__.py
dnnlab/utils/coco_map.py
dnnlab/utils/gpu.py
dnnlab/utils/performance.py
dnnlab-2.2.5.dist-info/LICENCE
dnnlab-2.2.5.dist-info/METADATA
dnnlab-2.2.5.dist-info/WHEEL
dnnlab-2.2.5.dist-info/top_level.txt
dnnlab-2.2.5.dist-info/RECORD
