Metadata-Version: 2.1
Name: dnnlab
Version: 2.2.5
Summary: DnnLab
Home-page: UNKNOWN
Author: Tobias Hoefer, Kevin Hirschmann Frederik Weishaeupl
Author-email: tobias.hoefer.hm@gmail.com,  kevin.hirschmann@noventi.de, Frederik.Weishaeupl@noventi.de
License: UNKNOWN
Platform: UNKNOWN
Classifier: Programming Language :: Python :: 3.6
Classifier: Programming Language :: Python :: 3.7
Classifier: License :: OSI Approved :: Apache Software License
Classifier: Operating System :: OS Independent
License-File: LICENCE
Requires-Dist: Cython
Requires-Dist: numpy
Requires-Dist: pycocotools (>=2.0.2)
Requires-Dist: Click (>=7.0)
Requires-Dist: opencv-python (==4.4.0.42)
Requires-Dist: imgaug (==0.4.0)
Requires-Dist: matplotlib (==3.3.0)
Provides-Extra: dev
